[{"pos": [1.0, 1.0, 1.0], "rot": [[1.0, 0.0, 0.0], [0.0, 1.0, 0.0], [0.0, 0.0, 1.0]], "size": 1, "material": {"emmitance": [0.5, 0.5, 0.5], "reflectance": [0.07083538822447133, 0.8210715325666051, 0.5271274797265023], "roughness": 0.0, "opacity": 0.0}, "childs": [0, 0, 0, 0, 0, 0, 0, 0], "is_leaf": 1, "is_none": 0}, {"pos": [-1.0, -1.0, -1.0], "rot": [[1.0, 0.0, 0.0], [0.0, 1.0, 0.0], [0.0, 0.0, 1.0]], "size": 1, "material": {"emmitance": [0.0, 0.0, 0.0], "reflectance": [0.32652715281631484, 0.9861998938994788, 0.5873710003935148], "roughness": 0.0, "opacity": 0.0}, "childs": [0, 0, 0, 0, 0, 0, 0, 0], "is_leaf": 1, "is_none": 0}, {"pos": [1.0, -1.0, -1.0], "rot": [[1.0, 0.0, 0.0], [0.0, 1.0, 0.0], [0.0, 0.0, 1.0]], "size": 1, "material": {"emmitance": [0.5, 0.5, 0.5], "reflectance": [0.534875078973978, 0.8020115082617844, 0.6323271357536117], "roughness": 0.0, "opacity": 0.0}, "childs": [0, 0, 0, 0, 0, 0, 0, 0], "is_leaf": 1, "is_none": 0}, {"pos": [1.0, 1.0, -1.0], "rot": [[1.0, 0.0, 0.0], [0.0, 1.0, 0.0], [0.0, 0.0, 1.0]], "size": 1, "material": {"emmitance": [0.0, 0.0, 0.0], "reflectance": [0.896346075979646, 0.7812139309367917, 0.6584175118629199], "roughness": 0.0, "opacity": 0.0}, "childs": [0, 0, 0, 0, 0, 0, 0, 0], "is_leaf": 1, "is_none": 0}, {"pos": [-1.0, 1.0, -1.0], "rot": [[1.0, 0.0, 0.0], [0.0, 1.0, 0.0], [0.0, 0.0, 1.0]], "size": 1, "material": {"emmitance": [0.0, 0.0, 0.0], "reflectance": [0.29803675264682605, 0.4445074214452295, 0.10801213709029145], "roughness": 0.0, "opacity": 0.0}, "childs": [0, 0, 0, 0, 0, 0, 0, 0], "is_leaf": 1, "is_none": 0}, {"pos": [1.0, -1.0, 1.0], "rot": [[1.0, 0.0, 0.0], [0.0, 1.0, 0.0], [0.0, 0.0, 1.0]], "size": 1, "material": {"emmitance": [0.5, 0.5, 0.5], "reflectance": [0.4751758111159585, 0.34794082294771955, 0.25039833788193244], "roughness": 0.0, "opacity": 0.0}, "childs": [0, 0, 0, 0, 0, 0, 0, 0], "is_leaf": 1, "is_none": 0}, {"pos": [-1.0, -1.0, 1.0], "rot": [[1.0, 0.0, 0.0], [0.0, 1.0, 0.0], [0.0, 0.0, 1.0]], "size": 1, "material": {"emmitance": [0.0, 0.0, 0.0], "reflectance": [0.2920982593657241, 0.0457539836438442, 0.35893756458228065], "roughness": 0.0, "opacity": 0.0}, "childs": [0, 0, 0, 0, 0, 0, 0, 0], "is_leaf": 1, "is_none": 0}, {"pos": [-1.0, 1.0, 1.0], "rot": [[1.0, 0.0, 0.0], [0.0, 1.0, 0.0], [0.0, 0.0, 1.0]], "size": 1, "material": {"emmitance": [0.0, 0.0, 0.0], "reflectance": [0.1762371889571841, 0.7116794953658593, 0.3251546656530001], "roughness": 0.0, "opacity": 0.0}, "childs": [0, 0, 0, 0, 0, 0, 0, 0], "is_leaf": 1, "is_none": 0}, {"pos": [0.0, 0.0, 0.0], "rot": [[1.0, 0.0, 0.0], [0.0, 1.0, 0.0], [0.0, 0.0, 1.0]], "size": 2, "material": {"emmitance": [1.0, 1.0, 1.0], "reflectance": [1.0, 1.0, 1.0], "roughness": 0.0, "opacity": 0.0}, "childs": [0, 1, 2, 3, 4, 5, 6, 7], "is_leaf": 0, "is_none": 0}]